adacs_django_playwright/__init__.py
adacs_django_playwright/adacs_django_playwright.py
adacs_django_playwright-1.2.0.dist-info/METADATA
adacs_django_playwright-1.2.0.dist-info/WHEEL
adacs_django_playwright-1.2.0.dist-info/RECORD
