Metadata-Version: 2.1
Name: adacs-django-playwright
Version: 1.2.0
Summary: 
Author: Asher
Author-email: jasherleslie@gmail.com
Requires-Python: >=3.10
Classifier: Programming Language :: Python :: 3
Classifier: Programming Language :: Python :: 3.10
Classifier: Programming Language :: Python :: 3.11
Classifier: Programming Language :: Python :: 3.12
Requires-Dist: django (>=5)
Requires-Dist: playwright (>=1.52.0,<2.0.0)
